olo/__init__.py
olo/_speedups.cpython-310-darwin.so
olo/_speedups.py
olo/ast_api.py
olo/cache.py
olo/cached_query.py
olo/compat.py
olo/context.py
olo/debug.py
olo/errors.py
olo/events.py
olo/expression.py
olo/field.py
olo/funcs.py
olo/interfaces.py
olo/key.py
olo/local.py
olo/logger.py
olo/migration.py
olo/model.py
olo/orm_types.py
olo/query.py
olo/session.py
olo/statement.py
olo/store.py
olo/transaction.py
olo/utils.cpython-310-darwin.so
olo/utils.py
olo/database/__init__.py
olo/database/mysql.py
olo/database/postgresql.py
olo/ext/__init__.py
olo/ext/declared.py
olo/ext/exported.py
olo/ext/hybrid.py
olo/ext/n.py
olo/libs/__init__.py
olo/libs/aes.py
olo/libs/cache.py
olo/libs/class_proxy.py
olo/libs/decompiling.py
olo/libs/pool.py
olo/libs/queue.py
olo/libs/compiler/__init__.py
olo/libs/compiler/ast.py
olo/libs/compiler/consts.py
olo/libs/compiler/eval.py
olo/libs/compiler/prelude_names.py
olo/libs/compiler/transformer.py
olo/libs/compiler/utils.py
olo/libs/compiler/translators/__init__.py
olo/libs/compiler/translators/ast_translator.py
olo/libs/compiler/translators/func_translator.py
olo/libs/compiler/translators/query_translator.py
olo/libs/compiler/translators/query_translator2.py
olo/mixins/__init__.py
olo/mixins/operations.py
olo/sql_ast_translators/__init__.py
olo/sql_ast_translators/mysql_sql_ast_translator.py
olo/sql_ast_translators/postgresql_sql_ast_translator.py
olo/sql_ast_translators/sql_ast_translator.py
olo/types/__init__.py
olo/types/json.py
tests/__init__.py
tests/base.py
tests/fixture.py
tests/test_ast_api.py
tests/test_cache.py
tests/test_cached_query.py
tests/test_database.py
tests/test_enum.py
tests/test_expression.py
tests/test_field.py
tests/test_funcs.py
tests/test_json.py
tests/test_migration.py
tests/test_model.py
tests/test_query.py
tests/test_store.py
tests/test_transaction.py
tests/test_utils.py
tests/utils.py
tests/libs/__init__.py
tests/libs/beansdb.py
tests/test_ext/__init__.py
tests/test_ext/test_declared.py
olo-0.5.0.dist-info/LICENSE
olo-0.5.0.dist-info/METADATA
olo-0.5.0.dist-info/WHEEL
olo-0.5.0.dist-info/top_level.txt
olo-0.5.0.dist-info/RECORD
