Metadata-Version: 2.1
Name: olo
Version: 0.5.0
Summary: ORM with intelligent and elegant cache manager
Home-page: https://github.com/yetone/olo
Author: yetone
Author-email: guanxipeng@douban.com
License: MIT License
Keywords: ORM,olo,cache,sqlstore
Platform: any
License-File: LICENSE
Requires-Dist: blinker (==1.4)
Requires-Dist: pycryptodomex (==3.14.1)
Requires-Dist: dill (==0.2.5)
Requires-Dist: dateparser (==0.7.2)
Requires-Dist: futures (==3.1.1)
Requires-Dist: decorator (==4.2.1)
Requires-Dist: pymysql (==0.9.1)
Requires-Dist: psycopg2 (==2.8.4)
Requires-Dist: typing-extensions (==3.7.4.1)
Requires-Dist: typeguard (==2.9.1)
Requires-Dist: tzlocal (==2.1)
Requires-Dist: regex (==2021.8.28)
